YasiBot/__init__.py
YasiBot/encryption.py
YasiBot/method.py
YasiBot/rubika.py
YasiBot/version.py
YasiBot-1.0.0.dist-info/LICENCE
YasiBot-1.0.0.dist-info/METADATA
YasiBot-1.0.0.dist-info/WHEEL
YasiBot-1.0.0.dist-info/top_level.txt
YasiBot-1.0.0.dist-info/RECORD
